additional_files/__init__.py
additional_files/loops.py
quick_sql-1.0.0.dist-info/LICENSE
quick_sql-1.0.0.dist-info/METADATA
quick_sql-1.0.0.dist-info/WHEEL
quick_sql-1.0.0.dist-info/top_level.txt
quick_sql-1.0.0.dist-info/RECORD
