Metadata-Version: 2.1
Name: quick-sql
Version: 1.0.0
Summary: A python library for sqlite3.
Home-page: https://github.com/pypa/sampleproject
Author: Kishcods
Author-email: kissancods@protonmail.com
License: UNKNOWN
Project-URL: Bug Tracker, https://github.com/pypa/sampleproject/issues
Platform: UNKNOWN
Classifier: Programming Language :: Python :: 3
Classifier: License :: OSI Approved :: MIT License
Classifier: Operating System :: OS Independent
Requires-Python: >=3.6
License-File: LICENSE
